asen_6008/__init__.py
asen_6008-2.0.0.dist-info/METADATA
asen_6008-2.0.0.dist-info/WHEEL
asen_6008-2.0.0.dist-info/top_level.txt
asen_6008-2.0.0.dist-info/RECORD
