Metadata-Version: 2.1
Name: asen-6008
Version: 2.0.0
Summary: Constants for CU Boulder's ASEN 6008
Home-page: https://github.com/nbelakovski/asen_6008
Author: Nickolai Belakovski
License: UNKNOWN
Platform: UNKNOWN
Classifier: Programming Language :: Python :: 3
Classifier: License :: Free For Educational Use
Classifier: Operating System :: OS Independent
Requires-Python: >=3.6
